builderer/__init__.py
builderer/__main__.py
builderer/_documentation.py
builderer/actions.py
builderer/builderer.py
builderer/config.py
builderer-2.0.0.dist-info/LICENSE
builderer-2.0.0.dist-info/METADATA
builderer-2.0.0.dist-info/WHEEL
builderer-2.0.0.dist-info/entry_points.txt
builderer-2.0.0.dist-info/top_level.txt
builderer-2.0.0.dist-info/RECORD
