Metadata-Version: 2.1
Name: builderer
Version: 2.0.0
Summary: Container based mono repo builder.
Home-page: https://github.com/florian-sattler/builderer/
Author: Florian Sattler
Author-email: dev@florian-sattler.de
License: MIT
Project-URL: Documentation, https://builderer.florian-sattler.de/
Project-URL: Source, https://github.com/florian-sattler/builderer/
Project-URL: Changelog, https://github.com/florian-sattler/builderer/blob/main/CHANGELOG.md
Project-URL: Tracker, https://github.com/florian-sattler/builderer/issues
Project-URL: Download, https://pypi.org/project/builderer/#files
Keywords: builderer,continuous integration,continuous delivery
Classifier: Development Status :: 5 - Production/Stable
Classifier: Intended Audience :: Developers
Classifier: Intended Audience :: Information Technology
Classifier: License :: OSI Approved :: MIT License
Classifier: Operating System :: OS Independent
Classifier: Programming Language :: Python :: 3
Classifier: Programming Language :: Python :: 3 :: Only
Classifier: Programming Language :: Python :: 3.10
Classifier: Programming Language :: Python :: 3.11
Requires-Python: >=3.10
License-File: LICENSE
Requires-Dist: pydantic (<2,>=1.9)
Requires-Dist: pyyaml (>=5.1)
